twtr/__init__.py
twtr/common.py
twtr/core/Tweet.py
twtr/core/Twitter.py
twtr/core/__init__.py
twtr_nuuuwan-1.0.7.dist-info/LICENSE
twtr_nuuuwan-1.0.7.dist-info/METADATA
twtr_nuuuwan-1.0.7.dist-info/WHEEL
twtr_nuuuwan-1.0.7.dist-info/top_level.txt
twtr_nuuuwan-1.0.7.dist-info/RECORD
